rag_llm_api_pipeline/__init__.py
rag_llm_api_pipeline/config_loader.py
rag_llm_api_pipeline/llm_wrapper.py
rag_llm_api_pipeline/loader.py
rag_llm_api_pipeline/retriever.py
rag_llm_api_pipeline/api/__init__.py
rag_llm_api_pipeline/api/server.py
rag_llm_api_pipeline/cli/__init__.py
rag_llm_api_pipeline/cli/main.py
rag_llm_api_pipeline/web/index.html
rag_llm_api_pipeline-0.7.1.dist-info/licenses/LICENSE
rag_llm_api_pipeline-0.7.1.dist-info/METADATA
rag_llm_api_pipeline-0.7.1.dist-info/WHEEL
rag_llm_api_pipeline-0.7.1.dist-info/entry_points.txt
rag_llm_api_pipeline-0.7.1.dist-info/top_level.txt
rag_llm_api_pipeline-0.7.1.dist-info/RECORD
