Metadata-Version: 2.4
Name: rag-llm-api-pipeline
Version: 0.7.1
Summary: Multimodal RAG pipeline for low-compute, local, real-world deployment
Home-page: https://github.com/pkbythebay29/ot-rag-llm-api
Author: pkbythebay29
Author-email: kannan@haztechrisk.org
Classifier: Programming Language :: Python :: 3
Classifier: License :: OSI Approved :: MIT License
Classifier: Operating System :: OS Independent
Requires-Python: >=3.8
License-File: LICENSE
Requires-Dist: torch>=2.2
Requires-Dist: transformers>=4.42.3
Requires-Dist: accelerate>=0.30.1
Requires-Dist: sentence-transformers>=2.7
Requires-Dist: faiss-cpu>=1.8.0
Requires-Dist: fastapi>=0.111
Requires-Dist: uvicorn[standard]>=0.30
Requires-Dist: pydantic>=2.7
Requires-Dist: pyyaml>=6.0.1
Requires-Dist: pytesseract>=0.3.10
Requires-Dist: pillow>=10.3
Requires-Dist: moviepy>=1.0.3
Requires-Dist: pymupdf>=1.24.5
Requires-Dist: openai-harmony>=0.0.3
Requires-Dist: tqdm>=4.66
Dynamic: author
Dynamic: author-email
Dynamic: classifier
Dynamic: description
Dynamic: description-content-type
Dynamic: home-page
Dynamic: license-file
Dynamic: requires-dist
Dynamic: requires-python
Dynamic: summary
